<?xml version="1.0" encoding="utf-8"?>
<LanguageData>
  <!--The following translations were generated by https://www.deepl.com/-->
  <NVA.ChangeRequiresRestart>Alle Änderungen erfordern einen Neustart, um wirksam zu werden.
Jede ausgewählte Kategorie entfernt alles, was mit</NVA.ChangeRequiresRestart>
  <NVA.RemoveHeadgear>Kopfbedeckung entfernen</NVA.RemoveHeadgear>
  <NVA.RemoveUpperBody>Oberkörper entfernen</NVA.RemoveUpperBody>
  <NVA.RemoveLowerBody>Unterkörper entfernen</NVA.RemoveLowerBody>
  <NVA.RemoveArmor>Rüstung entfernen</NVA.RemoveArmor>
  <NVA.ModVersion>Installierte Mod-Version: {0}</NVA.ModVersion>
</LanguageData>
